jinjabread/__init__.py
jinjabread/__main__.py
jinjabread/base.py
jinjabread/build.py
jinjabread/config.py
jinjabread/defaults.toml
jinjabread/errors.py
jinjabread/new.py
jinjabread/serve.py
jinjabread/utils.py
jinjabread-0.6.4.dist-info/licenses/LICENSE
jinjabread-0.6.4.dist-info/METADATA
jinjabread-0.6.4.dist-info/WHEEL
jinjabread-0.6.4.dist-info/top_level.txt
jinjabread-0.6.4.dist-info/RECORD
