Metadata-Version: 2.4
Name: jinjabread
Version: 0.6.4
Summary: An Python-based static site generator using Jinja templates.
License: MIT License
Project-URL: Website, http://jinjabread.com
Project-URL: Repository, https://github.com/jdeanwallace/jinjabread.git
Project-URL: Issues, https://github.com/jdeanwallace/jinjabread/issues
Requires-Python: >=3.9
License-File: LICENSE
Requires-Dist: jinja2==3.1.3
Requires-Dist: markdown==3.6
Requires-Dist: markdown-full-yaml-metadata==2.2.1
Requires-Dist: beautifulsoup4==4.12.3
Requires-Dist: werkzeug[watchdog]==3.0.1
Dynamic: license-file
